tox_gh_actions/__init__.py
tox_gh_actions/plugin.py
tox_gh_actions/py.typed
tox_gh_actions/version.py
tox_gh_actions-3.5.0.dist-info/licenses/LICENSE
tox_gh_actions-3.5.0.dist-info/METADATA
tox_gh_actions-3.5.0.dist-info/WHEEL
tox_gh_actions-3.5.0.dist-info/entry_points.txt
tox_gh_actions-3.5.0.dist-info/top_level.txt
tox_gh_actions-3.5.0.dist-info/RECORD
