Metadata-Version: 2.4
Name: tox-gh-actions
Version: 3.5.0
Summary: Seamless integration of tox into GitHub Actions
Author-email: Yusuke Miyazaki <miyazaki.dev@gmail.com>
Maintainer-email: Yusuke Miyazaki <miyazaki.dev@gmail.com>
License: MIT
Project-URL: Homepage, https://github.com/ymyzk/tox-gh-actions
Project-URL: Issue, https://github.com/ymyzk/tox-gh-actions/issues
Project-URL: Sponsor, https://github.com/sponsors/ymyzk
Keywords: tox,github,github-actions,ci,testing
Classifier: Development Status :: 5 - Production/Stable
Classifier: Framework :: tox
Classifier: Intended Audience :: Developers
Classifier: License :: OSI Approved :: MIT License
Classifier: Operating System :: OS Independent
Classifier: Programming Language :: Python :: 3
Classifier: Programming Language :: Python :: 3 :: Only
Classifier: Programming Language :: Python :: 3.7
Classifier: Programming Language :: Python :: 3.8
Classifier: Programming Language :: Python :: 3.9
Classifier: Programming Language :: Python :: 3.10
Classifier: Programming Language :: Python :: 3.11
Classifier: Programming Language :: Python :: 3.12
Classifier: Programming Language :: Python :: 3.13
Classifier: Programming Language :: Python :: Implementation :: CPython
Classifier: Programming Language :: Python :: Implementation :: PyPy
Classifier: Topic :: Software Development :: Libraries
Classifier: Topic :: Software Development :: Testing
Classifier: Topic :: Utilities
Classifier: Typing :: Typed
Requires-Python: >=3.7
License-File: LICENSE
Requires-Dist: tox<5,>=4
Provides-Extra: testing
Requires-Dist: devpi-process; extra == "testing"
Requires-Dist: mypy; platform_python_implementation == "CPython" and extra == "testing"
Requires-Dist: pre-commit; extra == "testing"
Requires-Dist: pytest>=7; extra == "testing"
Requires-Dist: pytest-cov>=4; extra == "testing"
Requires-Dist: pytest-mock>=3; extra == "testing"
Requires-Dist: pytest-randomly>=3; extra == "testing"
Dynamic: license-file
